people_finder/__init__.py
people_finder/recognition.py
people_finder-0.2.5b0.dist-info/LICENSE
people_finder-0.2.5b0.dist-info/METADATA
people_finder-0.2.5b0.dist-info/WHEEL
people_finder-0.2.5b0.dist-info/top_level.txt
people_finder-0.2.5b0.dist-info/RECORD
