Metadata-Version: 2.1
Name: people-finder
Version: 0.2.5b0
Summary: A tool to recognize people in images
Home-page: https://github.com/derogab/people-finder
Author: derogab
Author-email: derosagabriele@outlook.it
License: MIT
Keywords: people-finder
Platform: UNKNOWN
Classifier: Programming Language :: Python :: 3
Classifier: License :: OSI Approved :: MIT License
Classifier: Operating System :: OS Independent
Requires-Python: >=3.6
Requires-Dist: uuid
Requires-Dist: numpy
Requires-Dist: scikit-learn
Requires-Dist: opencv-python-headless
Requires-Dist: face-recognition
